uposatha/__init__.py
uposatha/calendar.py
uposatha/configure.py
uposatha/elements.py
uposatha/generate.py
uposatha-0.1.1.dist-info/METADATA
uposatha-0.1.1.dist-info/WHEEL
uposatha-0.1.1.dist-info/licenses/LICENCE
uposatha-0.1.1.dist-info/RECORD
