Metadata-Version: 2.1
Name: uposatha
Version: 0.1.1
Summary: API for the Thai Lunar Calendar
Project-URL: Homepage, https://github.com/jhanarato/uposatha
Project-URL: Bug Tracker, https://github.com/jhanarato/uposatha/issues
Author-email: Ajahn Jhanarato <jhanrato@gmail.com>
License-File: LICENCE
Classifier: License :: OSI Approved :: MIT License
Classifier: Operating System :: OS Independent
Classifier: Programming Language :: Python :: 3
Requires-Python: >=3.10
Provides-Extra: dev
Requires-Dist: pytest; extra == 'dev'
